chilo_api/__init__.py
chilo_api/__main__.py
chilo_api/gunicorn.py
chilo_api/cli/__init__.py
chilo_api/cli/commander.py
chilo_api/cli/importer.py
chilo_api/cli/logger.py
chilo_api/cli/scanner.py
chilo_api/cli/validator.py
chilo_api/cli/openapi/__init__.py
chilo_api/cli/openapi/arguments.py
chilo_api/cli/openapi/file_writer.py
chilo_api/cli/openapi/generator.py
chilo_api/cli/openapi/module.py
chilo_api/cli/server/__init__.py
chilo_api/cli/server/arguments.py
chilo_api/cli/server/grpc.py
chilo_api/cli/server/proto_parser.py
chilo_api/core/__init__.py
chilo_api/core/exception.py
chilo_api/core/executor.py
chilo_api/core/router.py
chilo_api/core/grpc/__init__.py
chilo_api/core/grpc/endpoint.py
chilo_api/core/grpc/mediator.py
chilo_api/core/grpc/pipeline.py
chilo_api/core/grpc/request.py
chilo_api/core/grpc/response.py
chilo_api/core/interfaces/__init__.py
chilo_api/core/interfaces/pipeline.py
chilo_api/core/interfaces/request.py
chilo_api/core/interfaces/response.py
chilo_api/core/logger/__init__.py
chilo_api/core/logger/common.py
chilo_api/core/logger/decorator.py
chilo_api/core/placeholders/__init__.py
chilo_api/core/placeholders/resolver.py
chilo_api/core/placeholders/wsgi.py
chilo_api/core/requirements/__init__.py
chilo_api/core/requirements/handler.py
chilo_api/core/resolver/__init__.py
chilo_api/core/resolver/cache.py
chilo_api/core/resolver/importer.py
chilo_api/core/resolver/scanner.py
chilo_api/core/rest/__init__.py
chilo_api/core/rest/endpoint.py
chilo_api/core/rest/json_helper.py
chilo_api/core/rest/pipeline.py
chilo_api/core/rest/request.py
chilo_api/core/rest/response.py
chilo_api/core/types/__init__.py
chilo_api/core/types/logger_settings.py
chilo_api/core/types/router_settings.py
chilo_api/core/types/server_settings.py
chilo_api/core/validator/__init__.py
chilo_api/core/validator/config.py
chilo_api/core/validator/openapi.py
chilo_api/core/validator/schema.py
chilo_api-2.0.2.dist-info/licenses/LICENSE
tests/__init__.py
tests/unit/__init__.py
tests/unit/cli/__init__.py
chilo_api-2.0.2.dist-info/METADATA
chilo_api-2.0.2.dist-info/WHEEL
chilo_api-2.0.2.dist-info/top_level.txt
chilo_api-2.0.2.dist-info/RECORD
