Metadata-Version: 2.4
Name: chilo_api
Version: 2.0.2
Summary: Chilo is a lightweight, form-meets-function, opinionated (yet highly configurable) api framework.
Home-page: https://github.com/dual/chilo.git
Author: Paul Cruse III
Author-email: paulcruse3@gmail.com
Classifier: Environment :: Web Environment
Classifier: Intended Audience :: Developers
Classifier: Topic :: Internet :: WWW/HTTP :: Dynamic Content
Classifier: Topic :: Software Development :: Libraries :: Python Modules
Classifier: Programming Language :: Python
Classifier: Programming Language :: Python :: 3
Classifier: Programming Language :: Python :: 3.6
Classifier: Programming Language :: Python :: 3.7
Classifier: Programming Language :: Python :: 3.8
Classifier: Programming Language :: Python :: 3.9
Classifier: Programming Language :: Python :: 3.10
Classifier: Programming Language :: Python :: 3.11
Requires-Python: >=3.0
License-File: LICENSE
Requires-Dist: art
Requires-Dist: icecream
Requires-Dist: grpcio
Requires-Dist: grpcio-tools
Requires-Dist: grpcio-reflection
Requires-Dist: jsonref
Requires-Dist: jsonschema
Requires-Dist: msgspec
Requires-Dist: openapi-spec-validator
Requires-Dist: parsy
Requires-Dist: pydantic
Requires-Dist: pyyaml
Requires-Dist: Werkzeug
Requires-Dist: xmltodict
Dynamic: author
Dynamic: author-email
Dynamic: classifier
Dynamic: description
Dynamic: description-content-type
Dynamic: home-page
Dynamic: license-file
Dynamic: requires-dist
Dynamic: requires-python
Dynamic: summary
